nonebot_plugin_crazy_thursday/__init__.py
nonebot_plugin_crazy_thursday/post.json
nonebot_plugin_crazy_thursday-0.2.8.dist-info/LICENSE
nonebot_plugin_crazy_thursday-0.2.8.dist-info/METADATA
nonebot_plugin_crazy_thursday-0.2.8.dist-info/WHEEL
nonebot_plugin_crazy_thursday-0.2.8.dist-info/RECORD
